{
    "github-pr.accessToken": "XXX",
    "editor.minimap.enabled": false,
    "files.autoSave": "afterDelay",
    "files.autoSaveDelay": 1000,
    "editor.wordWrap": "on",
    "editor.tabCompletion": true,
    "editor.autoIndent": true,
    "editor.fontSize": 14,
    "editor.renderControlCharacters": true,
    "editor.trimAutoWhitespace": true,
    "editor.formatOnSave": true,
    "terraform.format.enable": true,
    "editor.folding": false,
    "editor.glyphMargin": false,
    "json.format.enable": true,
    "window.restoreWindows": "all",
    "window.restoreFullscreen": true,
    "window.newWindowDimensions": "inherit",
    "window.zoomLevel": 0,
    "telemetry.enableCrashReporter": false,
    "telemetry.enableTelemetry": false,
    "spellchecker.language": "en_UK",
    "git.enableSmartCommit": true,
    "git.confirmSync": false,
    "markdown.preview.scrollEditorWithPreview": true,
    "workbench.editor.labelFormat": "default",
    "workbench.startupEditor": "newUntitledFile",
    "git.autofetch": true,
    "workbench.colorTheme": "Default Light+",
    "files.associations": {
        "Dockerfile-builder": "dockerfile",
        "Dockerfile-ubuntu": "dockerfile",
        "Dockerfile-alpine": "dockerfile",
        "Dockerfile-node": "dockerfile",
        "Dockerfile-composer": "dockerfile",
        "Dockerfile-php": "dockerfile",
        "Dockerfile-cache": "dockerfile",
        "Dockerfile-nginx": "dockerfile"
    }
}